nong/__init__.py
nong/nong.py
nong_nnrepos-0.111.dist-info/LICENSE
nong_nnrepos-0.111.dist-info/METADATA
nong_nnrepos-0.111.dist-info/WHEEL
nong_nnrepos-0.111.dist-info/entry_points.txt
nong_nnrepos-0.111.dist-info/top_level.txt
nong_nnrepos-0.111.dist-info/RECORD
